MANIFEST.in
README.rst
setup.py
docs/HISTORY.txt
docs/INSTALL.txt
docs/LICENSE.GPL
docs/LICENSE.txt
docs/UPGRADE.txt
src/collective/__init__.py
src/collective.flowplayer.egg-info/PKG-INFO
src/collective.flowplayer.egg-info/SOURCES.txt
src/collective.flowplayer.egg-info/dependency_links.txt
src/collective.flowplayer.egg-info/entry_points.txt
src/collective.flowplayer.egg-info/namespace_packages.txt
src/collective.flowplayer.egg-info/not-zip-safe
src/collective.flowplayer.egg-info/requires.txt
src/collective.flowplayer.egg-info/top_level.txt
src/collective/flowplayer/README.txt
src/collective/flowplayer/TODO.txt
src/collective/flowplayer/__init__.py
src/collective/flowplayer/behaviors.py
src/collective/flowplayer/configure.zcml
src/collective/flowplayer/dexterity.py
src/collective/flowplayer/dexterity.zcml
src/collective/flowplayer/events.py
src/collective/flowplayer/exportimport.py
src/collective/flowplayer/flv.py
src/collective/flowplayer/interfaces.py
src/collective/flowplayer/kupu.zcml
src/collective/flowplayer/media.py
src/collective/flowplayer/metadata_extraction.py
src/collective/flowplayer/metadata_extraction.txt
src/collective/flowplayer/migration.py
src/collective/flowplayer/profiles.zcml
src/collective/flowplayer/schemaextenders.py
src/collective/flowplayer/testing.py
src/collective/flowplayer/uninstall.py
src/collective/flowplayer/utils.py
src/collective/flowplayer/Extensions/Install.py
src/collective/flowplayer/browser/__init__.py
src/collective/flowplayer/browser/configure.zcml
src/collective/flowplayer/browser/file.pt
src/collective/flowplayer/browser/folder.pt
src/collective/flowplayer/browser/portlet.pt
src/collective/flowplayer/browser/portlet.py
src/collective/flowplayer/browser/uninstall.pt
src/collective/flowplayer/browser/view.py
src/collective/flowplayer/browser/css/entry.png
src/collective/flowplayer/browser/css/flowplayer-horizontal.css
src/collective/flowplayer/browser/css/flowplayer.css
src/collective/flowplayer/browser/css/gradient.png
src/collective/flowplayer/browser/css/left.png
src/collective/flowplayer/browser/css/play.png
src/collective/flowplayer/browser/css/right.png
src/collective/flowplayer/browser/flowplayer/README.txt
src/collective/flowplayer/browser/flowplayer/flowplayer.audio.swf
src/collective/flowplayer/browser/flowplayer/flowplayer.bwcheck.swf
src/collective/flowplayer/browser/flowplayer/flowplayer.controls.swf
