Metadata-Version: 1.1
Name: collective.flowplayer
Version: 4.2.1
Summary: A simple package using Flowplayer for video and audio content
Home-page: http://plone.org/products/collective-flowplayer
Author: Martin Aspeli
Author-email: optilude@gmail.com
License: GPL
Keywords: flv flash video plone
Platform: UNKNOWN
Classifier: Framework :: Plone
Classifier: Programming Language :: Python
Classifier: Topic :: Software Development :: Libraries :: Python Modules
